gait/.gitignore
gait/__init__.py
gait/cli.py
gait/llm.py
gait/log.py
gait/memory.py
gait/objects.py
gait/remote.py
gait/repo.py
gait/schema.py
gait/tokens.py
gait/verify.py
gait_ai-0.0.8.dist-info/METADATA
gait_ai-0.0.8.dist-info/WHEEL
gait_ai-0.0.8.dist-info/entry_points.txt
gait_ai-0.0.8.dist-info/licenses/LICENSE
gait_ai-0.0.8.dist-info/RECORD
