Metadata-Version: 2.4
Name: gait-ai
Version: 0.0.8
Summary: GAIT: git-like versioning for AI turns, commits, and context
Project-URL: Homepage, https://github.com/automateyournetwork/gait
Project-URL: Repository, https://github.com/automateyournetwork/gait
Project-URL: Issues, https://github.com/automateyournetwork/gait/issues
Author: John Capobianco
License: GPL-3.0-only
License-File: LICENSE
Keywords: ai,cli,git,llm,mlops,versioning
Classifier: Development Status :: 3 - Alpha
Classifier: Environment :: Console
Classifier: Intended Audience :: Developers
Classifier: License :: OSI Approved :: GNU General Public License v3 (GPLv3)
Classifier: Programming Language :: Python :: 3
Classifier: Programming Language :: Python :: 3 :: Only
Classifier: Programming Language :: Python :: 3.10
Classifier: Programming Language :: Python :: 3.11
Classifier: Programming Language :: Python :: 3.12
Classifier: Programming Language :: Python :: 3.13
Classifier: Topic :: Software Development :: Libraries
Classifier: Topic :: Software Development :: Version Control
Requires-Python: >=3.10
Requires-Dist: tiktoken>=0.12.0
Provides-Extra: dev
Requires-Dist: build>=1.2.0; extra == 'dev'
Requires-Dist: twine>=5.0.0; extra == 'dev'
